eqcctpro/__init__.py
eqcctpro/eqcct_tf_models.py
eqcctpro/functionality.py
eqcctpro/parallelization.py
eqcctpro/seisbench_models.py
eqcctpro/tools.py
eqcctpro-0.7.0.dist-info/METADATA
eqcctpro-0.7.0.dist-info/WHEEL
eqcctpro-0.7.0.dist-info/top_level.txt
eqcctpro-0.7.0.dist-info/RECORD
