Metadata-Version: 2.4
Name: eqcctpro
Version: 0.7.0
Summary: EQCCTPro: A Powerful Seismic Event Detection & Performance Optimization Toolkit
Author-email: Constantinos Skevofilax <constantinos.skevofilax@austin.utexas.edu>, Victor Salles <victor.salles@beg.utexas.edu>
Project-URL: Homepage, https://pypi.org/project/eqcctpro/
Project-URL: Repository, https://github.com/ut-beg-texnet/eqcct/tree/main/eqcctpro
Project-URL: Issues, https://github.com/ut-beg-texnet/eqcct/tree/main/eqcctpro/issues
Project-URL: Documentation, https://github.com/ut-beg-texnet/eqcct/blob/main/eqcctpro/README.md
Requires-Python: >=3.10.14
Requires-Dist: numpy==1.26.4
Requires-Dist: pandas==2.2.3
Requires-Dist: matplotlib==3.10.0
Requires-Dist: obspy==1.4.1
Requires-Dist: psutil==6.1.1
Requires-Dist: ray==2.42.1
Requires-Dist: tensorflow==2.20.0
Requires-Dist: keras==3.12.0
Requires-Dist: tensorboard==2.20.0
Requires-Dist: tensorboard-data-server==0.7.2
Requires-Dist: silence-tensorflow==1.2.3
Requires-Dist: scipy==1.15.1
Requires-Dist: protobuf==6.33.4
Requires-Dist: h5py==3.12.1
Requires-Dist: pynvml==12.0.0
Requires-Dist: torch==2.5.1
Requires-Dist: seisbench==0.10.2
Requires-Dist: nvidia-cudnn-cu12==9.17.1.4
Requires-Dist: requests==2.32.3
Requires-Dist: rich==13.9.4
Requires-Dist: shapely==2.1.0
